<!--
    SPDX-FileCopyrightText: 2023 Oliver Beard <olib141@outlook.com>
    SPDX-License-Identifier: MIT
-->

<kcfg xmlns="http://www.kde.org/standards/kcfg/1.0"
      xmlns:xsi="http://www.w3.org/2001/XMLSchema-instance"
      xsi:schemaLocation="http://www.kde.org/standards/kcfg/1.0
      http://www.kde.org/standards/kcfg/1.0/kcfg.xsd" >
    <kcfgfile name=""/>

    <group name="General">
        <entry name="sensors" type="String">
            <default></default>
        </entry>
    </group>

    <!--
    <group name="Appearance">
    </group>
    -->

    <group name="Misc">
        <entry name="updateInterval" type="Double">
            <default>1.0</default>
        </entry>
        <entry name="temperatureUnit" type="Enum">
            <choices>
                <choice name="celsius"/>
                <choice name="fahrenheit"/>
                <choice name="kelvin"/>
            </choices>
            <default>0</default>
        </entry>
    </group>
</kcfg>
